FeatherIconsQML
