Metadata-Version: 2.1
Name: PySide6-FeatherIcons-QML
Version: 0.1.2
Summary: Adds Feather Icons usable in QML for PySide6
Author: Cuberootex
License: MIT
Project-URL: Source code, https://github.com/Cuberootex/PySide6_FeatherIcons_QML
Keywords: PySide Qt PySide6 Feather Icons QML
Classifier: Operating System :: OS Independent
Requires-Python: >=3.8
License-File: LICENSE
